gettex_exchange/__init__.py
gettex_exchange/api.py
gettex_exchange/stock.py
gettex_exchange-1.2.0.dist-info/LICENSE
gettex_exchange-1.2.0.dist-info/METADATA
gettex_exchange-1.2.0.dist-info/WHEEL
gettex_exchange-1.2.0.dist-info/RECORD
