Metadata-Version: 2.3
Name: gettex-exchange
Version: 1.2.0
Summary: A Python client library for Gettex exchange
License: MIT
Author: Felix Börner
Requires-Python: >=3.13, <4.0
Classifier: License :: OSI Approved :: MIT License
Classifier: Programming Language :: Python :: 3
Classifier: Programming Language :: Python :: 3.13
Requires-Dist: beautifulsoup4 (>=4.13.3,<5.0.0)
Requires-Dist: loguru (>=0.7.0,<0.8.0)
Requires-Dist: pyjwt (>=2.10.1,<3.0.0)
Requires-Dist: requests (>=2.32.0,<3.0.0)
Requires-Dist: requests-cache (>=1.2.1,<2.0.0)
Requires-Dist: requests-ratelimiter (>=0.7.0,<0.8.0)
Project-URL: Homepage, https://github.com/escalate/gettex-exchange
Project-URL: Issues, https://github.com/escalate/gettex-exchange/issues
